buildpy_server_environments/plugin.py
buildpy_server_environments/__init__.py
buildpy_server_envs/plugin.py
buildpy_server_envs/__init__.py
buildpy_server_envs-0.1.1.dist-info/DESCRIPTION.rst
buildpy_server_envs-0.1.1.dist-info/entry_points.txt
buildpy_server_envs-0.1.1.dist-info/METADATA
buildpy_server_envs-0.1.1.dist-info/metadata.json
buildpy_server_envs-0.1.1.dist-info/RECORD
buildpy_server_envs-0.1.1.dist-info/top_level.txt
buildpy_server_envs-0.1.1.dist-info/WHEEL
